{
  "schemaVersion": 1,
  "exam": "ESAT",
  "entryCycle": "2027",
  "verifiedAt": "2026-07-17",
  "source": {
    "publisher": "UAT-UK",
    "title": "Course List 2027 Entry",
    "lastUpdated": "2026-04",
    "url": "https://uat-wp.s3.eu-west-2.amazonaws.com/wp-content/uploads/2026/04/01172717/Course_List_2027_Entry_Final.pdf"
  },
  "institutions": [
    { "id": "imperial", "name": "Imperial College London", "ucasCode": "I50" },
    { "id": "cambridge", "name": "University of Cambridge", "ucasCode": "C05" },
    { "id": "oxford", "name": "University of Oxford", "ucasCode": "O33" },
    { "id": "ucl", "name": "UCL", "ucasCode": "U80" }
  ],
  "programmes": [
    { "id": "imperial-h401", "institutionId": "imperial", "name": "MEng Aeronautical Engineering", "ucasCode": "H401", "rule": { "required": ["mathematics-1", "mathematics-2", "physics"], "choose": 0, "from": [], "totalModules": 3 } },
    { "id": "imperial-c700", "institutionId": "imperial", "name": "BSc Biochemistry", "ucasCode": "C700", "rule": { "required": ["mathematics-1", "chemistry", "biology"], "choose": 0, "from": [], "totalModules": 3 } },
    { "id": "imperial-c703", "institutionId": "imperial", "name": "MSci Biochemistry", "ucasCode": "C703", "rule": { "required": ["mathematics-1", "chemistry", "biology"], "choose": 0, "from": [], "totalModules": 3 } },
    { "id": "imperial-c7r1", "institutionId": "imperial", "name": "BSc Biochemistry with French", "ucasCode": "C7R1", "rule": { "required": ["mathematics-1", "chemistry", "biology"], "choose": 0, "from": [], "totalModules": 3 } },
    { "id": "imperial-c7r2", "institutionId": "imperial", "name": "BSc Biochemistry with German", "ucasCode": "C7R2", "rule": { "required": ["mathematics-1", "chemistry", "biology"], "choose": 0, "from": [], "totalModules": 3 } },
    { "id": "imperial-c7r4", "institutionId": "imperial", "name": "BSc Biochemistry with Spanish", "ucasCode": "C7R4", "rule": { "required": ["mathematics-1", "chemistry", "biology"], "choose": 0, "from": [], "totalModules": 3 } },
    { "id": "imperial-c100", "institutionId": "imperial", "name": "BSc Biological Sciences", "ucasCode": "C100", "rule": { "required": ["mathematics-1", "chemistry", "biology"], "choose": 0, "from": [], "totalModules": 3 } },
    { "id": "imperial-c103", "institutionId": "imperial", "name": "MSci Biological Sciences", "ucasCode": "C103", "rule": { "required": ["mathematics-1", "chemistry", "biology"], "choose": 0, "from": [], "totalModules": 3 } },
    { "id": "imperial-c1r1", "institutionId": "imperial", "name": "BSc Biological Sciences with French", "ucasCode": "C1R1", "rule": { "required": ["mathematics-1", "chemistry", "biology"], "choose": 0, "from": [], "totalModules": 3 } },
    { "id": "imperial-c1r2", "institutionId": "imperial", "name": "BSc Biological Sciences with German", "ucasCode": "C1R2", "rule": { "required": ["mathematics-1", "chemistry", "biology"], "choose": 0, "from": [], "totalModules": 3 } },
    { "id": "imperial-c1r4", "institutionId": "imperial", "name": "BSc Biological Sciences with Spanish", "ucasCode": "C1R4", "rule": { "required": ["mathematics-1", "chemistry", "biology"], "choose": 0, "from": [], "totalModules": 3 } },
    { "id": "imperial-j700", "institutionId": "imperial", "name": "BSc Biotechnology", "ucasCode": "J700", "rule": { "required": ["mathematics-1", "chemistry", "biology"], "choose": 0, "from": [], "totalModules": 3 } },
    { "id": "imperial-j703", "institutionId": "imperial", "name": "MSci Biotechnology", "ucasCode": "J703", "rule": { "required": ["mathematics-1", "chemistry", "biology"], "choose": 0, "from": [], "totalModules": 3 } },
    { "id": "imperial-j7r1", "institutionId": "imperial", "name": "BSc Biotechnology with French", "ucasCode": "J7R1", "rule": { "required": ["mathematics-1", "chemistry", "biology"], "choose": 0, "from": [], "totalModules": 3 } },
    { "id": "imperial-j7r2", "institutionId": "imperial", "name": "BSc Biotechnology with German", "ucasCode": "J7R2", "rule": { "required": ["mathematics-1", "chemistry", "biology"], "choose": 0, "from": [], "totalModules": 3 } },
    { "id": "imperial-j7r4", "institutionId": "imperial", "name": "BSc Biotechnology with Spanish", "ucasCode": "J7R4", "rule": { "required": ["mathematics-1", "chemistry", "biology"], "choose": 0, "from": [], "totalModules": 3 } },
    { "id": "imperial-h801", "institutionId": "imperial", "name": "MEng Chemical Engineering", "ucasCode": "H801", "rule": { "required": ["mathematics-1", "mathematics-2", "chemistry"], "choose": 0, "from": [], "totalModules": 3 } },
    { "id": "imperial-h201", "institutionId": "imperial", "name": "MEng Civil Engineering", "ucasCode": "H201", "rule": { "required": ["mathematics-1", "mathematics-2", "physics"], "choose": 0, "from": [], "totalModules": 3 } },
    { "id": "imperial-h202", "institutionId": "imperial", "name": "MEng Civil Engineering with a Year Abroad", "ucasCode": "H202", "rule": { "required": ["mathematics-1", "mathematics-2", "physics"], "choose": 0, "from": [], "totalModules": 3 } },
    { "id": "imperial-28g3", "institutionId": "imperial", "name": "MEng Design Engineering", "ucasCode": "28G3", "rule": { "required": ["mathematics-1", "mathematics-2"], "choose": 0, "from": [], "totalModules": 2 } },
    { "id": "imperial-c180", "institutionId": "imperial", "name": "BSc Ecology and Environmental Biology", "ucasCode": "C180", "rule": { "required": ["mathematics-1", "chemistry", "biology"], "choose": 0, "from": [], "totalModules": 3 } },
    { "id": "imperial-h600", "institutionId": "imperial", "name": "BEng Electrical and Electronic Engineering", "ucasCode": "H600", "rule": { "required": ["mathematics-1", "mathematics-2", "physics"], "choose": 0, "from": [], "totalModules": 3 } },
    { "id": "imperial-h604", "institutionId": "imperial", "name": "MEng Electrical and Electronic Engineering", "ucasCode": "H604", "rule": { "required": ["mathematics-1", "mathematics-2", "physics"], "choose": 0, "from": [], "totalModules": 3 } },
    { "id": "imperial-h6n2", "institutionId": "imperial", "name": "MEng Electrical and Electronic Engineering with Management", "ucasCode": "H6N2", "rule": { "required": ["mathematics-1", "mathematics-2", "physics"], "choose": 0, "from": [], "totalModules": 3 } },
    { "id": "imperial-hg65", "institutionId": "imperial", "name": "BEng Electronic and Information Engineering", "ucasCode": "HG65", "rule": { "required": ["mathematics-1", "mathematics-2", "physics"], "choose": 0, "from": [], "totalModules": 3 } },
    { "id": "imperial-gh56", "institutionId": "imperial", "name": "MEng Electronic and Information Engineering", "ucasCode": "GH56", "rule": { "required": ["mathematics-1", "mathematics-2", "physics"], "choose": 0, "from": [], "totalModules": 3 } },
    { "id": "imperial-h301", "institutionId": "imperial", "name": "MEng Mechanical Engineering", "ucasCode": "H301", "rule": { "required": ["mathematics-1", "mathematics-2", "physics"], "choose": 0, "from": [], "totalModules": 3 } },
    { "id": "imperial-c500", "institutionId": "imperial", "name": "BSc Microbiology", "ucasCode": "C500", "rule": { "required": ["mathematics-1", "chemistry", "biology"], "choose": 0, "from": [], "totalModules": 3 } },
    { "id": "imperial-f300", "institutionId": "imperial", "name": "BSc Physics", "ucasCode": "F300", "rule": { "required": ["mathematics-1", "mathematics-2", "physics"], "choose": 0, "from": [], "totalModules": 3 } },
    { "id": "imperial-f303", "institutionId": "imperial", "name": "MSci Physics", "ucasCode": "F303", "rule": { "required": ["mathematics-1", "mathematics-2", "physics"], "choose": 0, "from": [], "totalModules": 3 } },
    { "id": "imperial-f309", "institutionId": "imperial", "name": "MSci Physics with a Year Abroad", "ucasCode": "F309", "rule": { "required": ["mathematics-1", "mathematics-2", "physics"], "choose": 0, "from": [], "totalModules": 3 } },
    { "id": "imperial-f325", "institutionId": "imperial", "name": "BSc Physics with Theoretical Physics", "ucasCode": "F325", "rule": { "required": ["mathematics-1", "mathematics-2", "physics"], "choose": 0, "from": [], "totalModules": 3 } },
    { "id": "imperial-f390", "institutionId": "imperial", "name": "MSci Physics with Theoretical Physics", "ucasCode": "F390", "rule": { "required": ["mathematics-1", "mathematics-2", "physics"], "choose": 0, "from": [], "totalModules": 3 } },

    { "id": "cambridge-h810", "institutionId": "cambridge", "name": "BA/MEng Chemical Engineering and Biotechnology", "ucasCode": "H810", "rule": { "required": ["mathematics-1"], "choose": 2, "from": ["biology", "chemistry", "physics", "mathematics-2"], "totalModules": 3 } },
    { "id": "cambridge-h100", "institutionId": "cambridge", "name": "BA/MEng Engineering", "ucasCode": "H100", "rule": { "required": ["mathematics-1", "mathematics-2", "physics"], "choose": 0, "from": [], "totalModules": 3 } },
    { "id": "cambridge-bcf0", "institutionId": "cambridge", "name": "BA/MSci Natural Sciences", "ucasCode": "BCF0", "rule": { "required": ["mathematics-1"], "choose": 2, "from": ["biology", "chemistry", "physics", "mathematics-2"], "totalModules": 3 } },
    { "id": "cambridge-d100", "institutionId": "cambridge", "name": "VetMB Veterinary Medicine", "ucasCode": "D100", "rule": { "required": ["mathematics-1"], "choose": 2, "from": ["biology", "chemistry", "physics", "mathematics-2"], "totalModules": 3 } },

    { "id": "oxford-bc98", "institutionId": "oxford", "name": "Biomedical Sciences", "ucasCode": "BC98", "rule": { "required": ["mathematics-1"], "choose": 2, "from": ["biology", "chemistry", "physics", "mathematics-2"], "totalModules": 3 } },
    { "id": "oxford-h811", "institutionId": "oxford", "name": "Biomedical Engineering", "ucasCode": "H811", "rule": { "required": ["mathematics-1", "mathematics-2", "physics"], "choose": 0, "from": [], "totalModules": 3 } },
    { "id": "oxford-h81f", "institutionId": "oxford", "name": "Biomedical Engineering with Foundation Year", "ucasCode": "H81F", "rule": { "required": ["mathematics-1", "mathematics-2", "physics"], "choose": 0, "from": [], "totalModules": 3 } },
    { "id": "oxford-h800", "institutionId": "oxford", "name": "Chemical Engineering", "ucasCode": "H800", "rule": { "required": ["mathematics-1", "mathematics-2", "physics"], "choose": 0, "from": [], "totalModules": 3 } },
    { "id": "oxford-h80f", "institutionId": "oxford", "name": "Chemical Engineering with Foundation Year", "ucasCode": "H80F", "rule": { "required": ["mathematics-1", "mathematics-2", "physics"], "choose": 0, "from": [], "totalModules": 3 } },
    { "id": "oxford-h200", "institutionId": "oxford", "name": "Civil Engineering", "ucasCode": "H200", "rule": { "required": ["mathematics-1", "mathematics-2", "physics"], "choose": 0, "from": [], "totalModules": 3 } },
    { "id": "oxford-h20f", "institutionId": "oxford", "name": "Civil Engineering with Foundation Year", "ucasCode": "H20F", "rule": { "required": ["mathematics-1", "mathematics-2", "physics"], "choose": 0, "from": [], "totalModules": 3 } },
    { "id": "oxford-h620", "institutionId": "oxford", "name": "Electrical Engineering", "ucasCode": "H620", "rule": { "required": ["mathematics-1", "mathematics-2", "physics"], "choose": 0, "from": [], "totalModules": 3 } },
    { "id": "oxford-h62f", "institutionId": "oxford", "name": "Electrical Engineering with Foundation Year", "ucasCode": "H62F", "rule": { "required": ["mathematics-1", "mathematics-2", "physics"], "choose": 0, "from": [], "totalModules": 3 } },
    { "id": "oxford-h100", "institutionId": "oxford", "name": "Engineering Science", "ucasCode": "H100", "rule": { "required": ["mathematics-1", "mathematics-2", "physics"], "choose": 0, "from": [], "totalModules": 3 } },
    { "id": "oxford-h10f", "institutionId": "oxford", "name": "Engineering with Foundation Year", "ucasCode": "H10F", "rule": { "required": ["mathematics-1", "mathematics-2", "physics"], "choose": 0, "from": [], "totalModules": 3 } },
    { "id": "oxford-h630", "institutionId": "oxford", "name": "Information Engineering", "ucasCode": "H630", "rule": { "required": ["mathematics-1", "mathematics-2", "physics"], "choose": 0, "from": [], "totalModules": 3 } },
    { "id": "oxford-h63f", "institutionId": "oxford", "name": "Information Engineering with Foundation Year", "ucasCode": "H63F", "rule": { "required": ["mathematics-1", "mathematics-2", "physics"], "choose": 0, "from": [], "totalModules": 3 } },
    { "id": "oxford-f303", "institutionId": "oxford", "name": "Physics", "ucasCode": "F303", "rule": { "required": ["mathematics-1", "mathematics-2", "physics"], "choose": 0, "from": [], "totalModules": 3 } },
    { "id": "oxford-vf53", "institutionId": "oxford", "name": "Physics and Philosophy", "ucasCode": "VF53", "rule": { "required": ["mathematics-1", "mathematics-2", "physics"], "choose": 0, "from": [], "totalModules": 3 } },
    { "id": "oxford-h300", "institutionId": "oxford", "name": "Mechanical Engineering", "ucasCode": "H300", "rule": { "required": ["mathematics-1", "mathematics-2", "physics"], "choose": 0, "from": [], "totalModules": 3 } },
    { "id": "oxford-h30f", "institutionId": "oxford", "name": "Mechanical Engineering with Foundation Year", "ucasCode": "H30F", "rule": { "required": ["mathematics-1", "mathematics-2", "physics"], "choose": 0, "from": [], "totalModules": 3 } },

    { "id": "ucl-h600", "institutionId": "ucl", "name": "BEng Electronic and Electrical Engineering", "ucasCode": "H600", "rule": { "required": ["mathematics-1"], "choose": 2, "from": ["biology", "chemistry", "physics", "mathematics-2"], "totalModules": 3 } },
    { "id": "ucl-h601", "institutionId": "ucl", "name": "MEng Electronic and Electrical Engineering", "ucasCode": "H601", "rule": { "required": ["mathematics-1"], "choose": 2, "from": ["biology", "chemistry", "physics", "mathematics-2"], "totalModules": 3 } }
  ]
}
